etsi/failprint/__init__.py
etsi/failprint/cluster.py
etsi/failprint/core.py
etsi/failprint/correlate.py
etsi/failprint/counterfactuals.py
etsi/failprint/cv_embedder.py
etsi/failprint/cv_features.py
etsi/failprint/data_validation.py
etsi/failprint/explain.py
etsi/failprint/nlp.py
etsi/failprint/nlp_features.py
etsi/failprint/report.py
etsi/failprint/segmenter.py
etsi/failprint/utils.py
etsi_failprint-0.2.0.dist-info/licenses/LICENSE
etsi_failprint-0.2.0.dist-info/METADATA
etsi_failprint-0.2.0.dist-info/WHEEL
etsi_failprint-0.2.0.dist-info/top_level.txt
etsi_failprint-0.2.0.dist-info/RECORD
