Metadata-Version: 2.4
Name: etsi-failprint
Version: 0.2.0
Summary: Automated failure pattern detection and root-cause analysis for ML workflows
Author-email: etsi <etsi.hq@gmail.com>
License: BSD-2-Clause
Project-URL: Homepage, https://github.com/etsi-ai/etsi-failprint
Project-URL: Repository, https://github.com/etsi-ai/etsi-failprint
Project-URL: Bug Tracker, https://github.com/etsi-ai/etsi-failprint/issues
Keywords: MLOps,failure-analysis,diagnostics,model-monitoring,debugging,root-cause
Classifier: Development Status :: 3 - Alpha
Classifier: Intended Audience :: Developers
Classifier: Topic :: Software Development :: Libraries
Classifier: Topic :: Scientific/Engineering :: Artificial Intelligence
Classifier: License :: OSI Approved :: BSD License
Classifier: Programming Language :: Python :: 3
Classifier: Programming Language :: Python :: 3.8
Classifier: Programming Language :: Python :: 3.9
Classifier: Programming Language :: Python :: 3.10
Classifier: Programming Language :: Python :: 3.11
Requires-Python: >=3.8
License-File: LICENSE
Requires-Dist: pandas
Requires-Dist: numpy
Requires-Dist: scikit-learn
Requires-Dist: shap
Requires-Dist: tabulate
Requires-Dist: torch
Requires-Dist: torchvision
Requires-Dist: sentence-transformers
Requires-Dist: spacy
Requires-Dist: textblob
Requires-Dist: Pillow
Dynamic: license-file
